oss_internal/__init__.py
oss_internal/oss_download.py
oss_internal/oss_upload.py
oss_internal/schemas/__init__.py
oss_internal/schemas/error.py
oss_internal/utils/__init__.py
oss_internal/utils/progress_display.py
oss_internal/utils/signed_url_generator.py
oss_internal-1.7.3.dist-info/licenses/LICENSE
oss_internal-1.7.3.dist-info/METADATA
oss_internal-1.7.3.dist-info/WHEEL
oss_internal-1.7.3.dist-info/top_level.txt
oss_internal-1.7.3.dist-info/RECORD
