Metadata-Version: 2.4
Name: oss_internal
Version: 1.7.3
Summary: An internal utility package for Aliyun OSS operations.
Author: Guan Xingjian
Author-email: edward@aputure.com
License: MIT
Classifier: Programming Language :: Python :: 3
Classifier: Operating System :: OS Independent
Classifier: License :: OSI Approved :: MIT License
Classifier: Intended Audience :: Developers
Classifier: Topic :: Software Development :: Libraries
Requires-Python: >=3.11
License-File: LICENSE
Requires-Dist: aiohappyeyeballs
Requires-Dist: aiohttp
Requires-Dist: aiosignal
Requires-Dist: aliyun-python-sdk-core
Requires-Dist: aliyun-python-sdk-kms
Requires-Dist: asyncio-oss
Requires-Dist: attrs
Requires-Dist: certifi
Requires-Dist: cffi
Requires-Dist: charset-normalizer
Requires-Dist: crcmod
Requires-Dist: cryptography
Requires-Dist: frozenlist
Requires-Dist: idna
Requires-Dist: jmespath
Requires-Dist: multidict
Requires-Dist: oss2
Requires-Dist: propcache
Requires-Dist: pycparser
Requires-Dist: pycryptodome
Requires-Dist: requests
Requires-Dist: six
Requires-Dist: tqdm
Requires-Dist: urllib3
Requires-Dist: yarl
Requires-Dist: alibabacloud_oss_v2
Dynamic: author
Dynamic: author-email
Dynamic: classifier
Dynamic: description
Dynamic: description-content-type
Dynamic: license
Dynamic: license-file
Dynamic: requires-dist
Dynamic: requires-python
Dynamic: summary
